bazario/__init__.py
bazario/chain.py
bazario/dispatcher.py
bazario/exceptions.py
bazario/markers.py
bazario/py.typed
bazario/registry.py
bazario/abc/__init__.py
bazario/abc/handler.py
bazario/abc/pipeline_behavior.py
bazario/abc/publisher.py
bazario/abc/resolver.py
bazario/abc/sender.py
bazario/asyncio/__init__.py
bazario/asyncio/chain.py
bazario/asyncio/dispatcher.py
bazario/asyncio/registry.py
bazario/asyncio/abc/__init__.py
bazario/asyncio/abc/handler.py
bazario/asyncio/abc/pipeline_behavior.py
bazario/asyncio/abc/publisher.py
bazario/asyncio/abc/resolver.py
bazario/asyncio/abc/sender.py
bazario/asyncio/resolvers/__init__.py
bazario/asyncio/resolvers/dishka.py
bazario/resolvers/__init__.py
bazario/resolvers/dishka.py
bazario/resolvers/punq.py
bazario-0.4.2.dist-info/LICENSE
bazario-0.4.2.dist-info/METADATA
bazario-0.4.2.dist-info/WHEEL
bazario-0.4.2.dist-info/top_level.txt
bazario-0.4.2.dist-info/RECORD
