Metadata-Version: 2.2
Name: bazario
Version: 0.4.2
Summary: Lightweight handler routing library for modular apps.
Author-email: Alim Abrekov <chessinmind17@yandex.ru>
Project-URL: Source, https://github.com/chessenjoyer17/bazario
Project-URL: Homepage, https://github.com/chessenjoyer17/bazario
Project-URL: Bug Tracker, https://github.com/chessenjoyer17/bazario/issues
Project-URL: Documentation, https://chessenjoyer17.github.io/bazario/
Classifier: Programming Language :: Python :: 3.10
Classifier: Programming Language :: Python :: 3.11
Classifier: Programming Language :: Python :: 3.12
Classifier: Programming Language :: Python :: 3.13
Classifier: Topic :: Software Development :: Libraries
Classifier: Typing :: Typed
Classifier: Intended Audience :: Developers
Classifier: License :: OSI Approved :: MIT License
Classifier: Operating System :: OS Independent
Requires-Python: >=3.10
License-File: LICENSE
Provides-Extra: test
Requires-Dist: pytest; extra == "test"
Provides-Extra: lint
Requires-Dist: ruff; extra == "lint"
Requires-Dist: mypy; extra == "lint"
Provides-Extra: dishka
Requires-Dist: dishka; extra == "dishka"
Provides-Extra: punq
Requires-Dist: punq; extra == "punq"
